{
  "project_name": "localtest",
  "timeline": {
    "name": "29.97 fps",
    "fps": 29.97,
    "project_fps": 29.97,
    "start_timecode": "00:00:00:00",
    "curr_timecode": "",
    "video_track_items": [
      {
        "bmd_item": null,
        "bmd_mpi": null,
        "name": "compound 29.97 (maybe)",
        "id": "compound 29.97 (maybe)-video-1--0.0",
        "track_type": "video",
        "track_index": 1,
        "source_file_path": "",
        "start_frame": 0,
        "end_frame": 29483,
        "source_start_frame": 0,
        "source_end_frame": 29483,
        "duration": 29483,
        "edit_instructions": [],
        "source_channel": 0,
        "type": "Zusammengesetzt",
        "nested_clips": [
          {
            "source_file_path": "/home/oliwoli/Videos/P1466663.MOV",
            "processed_file_name": "f4d8a3a878cb54a482beef75815913da.wav",
            "start_frame": 0,
            "end_frame": 324.99967499999997,
            "source_start_frame": 793.9992060001107,
            "source_end_frame": 1118.9988810001107,
            "duration": 324.99967499999997,
            "source_channel": 1,
            "edit_instructions": []
          },
          {
            "source_file_path": "/home/oliwoli/Videos/P1466663.MOV",
            "processed_file_name": "f4d8a3a878cb54a482beef75815913da.wav",
            "start_frame": 398,
            "end_frame": 29482.970915,
            "source_start_frame": 0,
            "source_end_frame": 29084.970915,
            "duration": 29084.970915,
            "source_channel": 1,
            "edit_instructions": []
          }
        ]
      }
    ],
    "audio_track_items": [
      {
        "bmd_item": null,
        "bmd_mpi": null,
        "name": "compound 29.97 (maybe)",
        "id": "compound 29.97 (maybe)-audio-1--0.0",
        "track_type": "audio",
        "track_index": 1,
        "source_file_path": "/home/oliwoli/my-repos/HushCut/build/bin/wav_files/dee25ad1-973f-5887-9287-a5eb19a44b46.wav",
        "processed_file_name": "dee25ad1-973f-5887-9287-a5eb19a44b46.wav",
        "start_frame": 0,
        "end_frame": 29483,
        "source_start_frame": 0,
        "source_end_frame": 29483,
        "duration": 29483,
        "edit_instructions": [
          {
            "source_start_frame": 0,
            "source_end_frame": 313.999999999,
            "start_frame": 0,
            "end_frame": 313,
            "enabled": true
          },
          {
            "source_start_frame": 314,
            "source_end_frame": 720.999999999,
            "start_frame": 314,
            "end_frame": 720,
            "enabled": false
          },
          {
            "source_start_frame": 721,
            "source_end_frame": 785.999999999,
            "start_frame": 721,
            "end_frame": 785,
            "enabled": true
          },
          {
            "source_start_frame": 786,
            "source_end_frame": 1199.999999999,
            "start_frame": 786,
            "end_frame": 1199,
            "enabled": false
          },
          {
            "source_start_frame": 1200,
            "source_end_frame": 1510.999999999,
            "start_frame": 1200,
            "end_frame": 1510,
            "enabled": true
          },
          {
            "source_start_frame": 1511,
            "source_end_frame": 2295.999999999,
            "start_frame": 1511,
            "end_frame": 2295,
            "enabled": false
          },
          {
            "source_start_frame": 2296,
            "source_end_frame": 4950.999999999,
            "start_frame": 2296,
            "end_frame": 4950,
            "enabled": true
          },
          {
            "source_start_frame": 4951,
            "source_end_frame": 5066.999999999,
            "start_frame": 4951,
            "end_frame": 5066,
            "enabled": false
          },
          {
            "source_start_frame": 5067,
            "source_end_frame": 5322.999999999,
            "start_frame": 5067,
            "end_frame": 5322,
            "enabled": true
          },
          {
            "source_start_frame": 5323,
            "source_end_frame": 5469.999999999,
            "start_frame": 5323,
            "end_frame": 5469,
            "enabled": false
          },
          {
            "source_start_frame": 5470,
            "source_end_frame": 6675.999999999,
            "start_frame": 5470,
            "end_frame": 6675,
            "enabled": true
          },
          {
            "source_start_frame": 6676,
            "source_end_frame": 6812.999999999,
            "start_frame": 6676,
            "end_frame": 6812,
            "enabled": false
          },
          {
            "source_start_frame": 6813,
            "source_end_frame": 8619.999999999,
            "start_frame": 6813,
            "end_frame": 8619,
            "enabled": true
          },
          {
            "source_start_frame": 8620,
            "source_end_frame": 8823.999999999,
            "start_frame": 8620,
            "end_frame": 8823,
            "enabled": false
          },
          {
            "source_start_frame": 8824,
            "source_end_frame": 9170.999999999,
            "start_frame": 8824,
            "end_frame": 9170,
            "enabled": true
          },
          {
            "source_start_frame": 9171,
            "source_end_frame": 9253.999999999,
            "start_frame": 9171,
            "end_frame": 9253,
            "enabled": false
          },
          {
            "source_start_frame": 9254,
            "source_end_frame": 11852.999999999,
            "start_frame": 9254,
            "end_frame": 11852,
            "enabled": true
          },
          {
            "source_start_frame": 11853,
            "source_end_frame": 12252.999999999,
            "start_frame": 11853,
            "end_frame": 12252,
            "enabled": false
          },
          {
            "source_start_frame": 12253,
            "source_end_frame": 13636.999999999,
            "start_frame": 12253,
            "end_frame": 13636,
            "enabled": true
          },
          {
            "source_start_frame": 13637,
            "source_end_frame": 14091.999999999,
            "start_frame": 13637,
            "end_frame": 14091,
            "enabled": false
          },
          {
            "source_start_frame": 14092,
            "source_end_frame": 16273.999999999,
            "start_frame": 14092,
            "end_frame": 16273,
            "enabled": true
          },
          {
            "source_start_frame": 16274,
            "source_end_frame": 16765.999999999,
            "start_frame": 16274,
            "end_frame": 16765,
            "enabled": false
          },
          {
            "source_start_frame": 16766,
            "source_end_frame": 19730.999999999,
            "start_frame": 16766,
            "end_frame": 19730,
            "enabled": true
          },
          {
            "source_start_frame": 19731,
            "source_end_frame": 20021.999999999,
            "start_frame": 19731,
            "end_frame": 20021,
            "enabled": false
          },
          {
            "source_start_frame": 20022,
            "source_end_frame": 21539.999999999,
            "start_frame": 20022,
            "end_frame": 21539,
            "enabled": true
          },
          {
            "source_start_frame": 21540,
            "source_end_frame": 22605.999999999,
            "start_frame": 21540,
            "end_frame": 22605,
            "enabled": false
          },
          {
            "source_start_frame": 22606,
            "source_end_frame": 22785.999999999,
            "start_frame": 22606,
            "end_frame": 22785,
            "enabled": true
          },
          {
            "source_start_frame": 22786,
            "source_end_frame": 23050.999999999,
            "start_frame": 22786,
            "end_frame": 23050,
            "enabled": false
          },
          {
            "source_start_frame": 23051,
            "source_end_frame": 23082.999999999,
            "start_frame": 23051,
            "end_frame": 23082,
            "enabled": true
          },
          {
            "source_start_frame": 23083,
            "source_end_frame": 23141.999999999,
            "start_frame": 23083,
            "end_frame": 23141,
            "enabled": false
          },
          {
            "source_start_frame": 23142,
            "source_end_frame": 25490.999999999,
            "start_frame": 23142,
            "end_frame": 25490,
            "enabled": true
          },
          {
            "source_start_frame": 25491,
            "source_end_frame": 25708.999999999,
            "start_frame": 25491,
            "end_frame": 25708,
            "enabled": false
          },
          {
            "source_start_frame": 25709,
            "source_end_frame": 25740.999999999,
            "start_frame": 25709,
            "end_frame": 25740,
            "enabled": true
          },
          {
            "source_start_frame": 25741,
            "source_end_frame": 25873.999999999,
            "start_frame": 25741,
            "end_frame": 25873,
            "enabled": false
          },
          {
            "source_start_frame": 25874,
            "source_end_frame": 25904.999999999,
            "start_frame": 25874,
            "end_frame": 25904,
            "enabled": true
          },
          {
            "source_start_frame": 25905,
            "source_end_frame": 26068.999999999,
            "start_frame": 25905,
            "end_frame": 26068,
            "enabled": false
          },
          {
            "source_start_frame": 26069,
            "source_end_frame": 26895.999999999,
            "start_frame": 26069,
            "end_frame": 26895,
            "enabled": true
          },
          {
            "source_start_frame": 26896,
            "source_end_frame": 26972.999999999,
            "start_frame": 26896,
            "end_frame": 26972,
            "enabled": false
          },
          {
            "source_start_frame": 26973,
            "source_end_frame": 27050.999999999,
            "start_frame": 26973,
            "end_frame": 27050,
            "enabled": true
          },
          {
            "source_start_frame": 27051,
            "source_end_frame": 27134.999999999,
            "start_frame": 27051,
            "end_frame": 27134,
            "enabled": false
          },
          {
            "source_start_frame": 27135,
            "source_end_frame": 27164.999999999,
            "start_frame": 27135,
            "end_frame": 27164,
            "enabled": true
          },
          {
            "source_start_frame": 27165,
            "source_end_frame": 27426.999999999,
            "start_frame": 27165,
            "end_frame": 27426,
            "enabled": false
          },
          {
            "source_start_frame": 27427,
            "source_end_frame": 27467.999999999,
            "start_frame": 27427,
            "end_frame": 27467,
            "enabled": true
          },
          {
            "source_start_frame": 27468,
            "source_end_frame": 27623.999999999,
            "start_frame": 27468,
            "end_frame": 27623,
            "enabled": false
          },
          {
            "source_start_frame": 27624,
            "source_end_frame": 27655.999999999,
            "start_frame": 27624,
            "end_frame": 27655,
            "enabled": true
          },
          {
            "source_start_frame": 27656,
            "source_end_frame": 27765.999999999,
            "start_frame": 27656,
            "end_frame": 27765,
            "enabled": false
          },
          {
            "source_start_frame": 27766,
            "source_end_frame": 27854.999999999,
            "start_frame": 27766,
            "end_frame": 27854,
            "enabled": true
          },
          {
            "source_start_frame": 27855,
            "source_end_frame": 27911.999999999,
            "start_frame": 27855,
            "end_frame": 27911,
            "enabled": false
          },
          {
            "source_start_frame": 27912,
            "source_end_frame": 27952.999999999,
            "start_frame": 27912,
            "end_frame": 27952,
            "enabled": true
          },
          {
            "source_start_frame": 27953,
            "source_end_frame": 28034.999999999,
            "start_frame": 27953,
            "end_frame": 28034,
            "enabled": false
          },
          {
            "source_start_frame": 28035,
            "source_end_frame": 28083.999999999,
            "start_frame": 28035,
            "end_frame": 28083,
            "enabled": true
          },
          {
            "source_start_frame": 28084,
            "source_end_frame": 28392.999999999,
            "start_frame": 28084,
            "end_frame": 28392,
            "enabled": false
          },
          {
            "source_start_frame": 28393,
            "source_end_frame": 28504.999999999,
            "start_frame": 28393,
            "end_frame": 28504,
            "enabled": true
          },
          {
            "source_start_frame": 28505,
            "source_end_frame": 28977.999999999,
            "start_frame": 28505,
            "end_frame": 28977,
            "enabled": false
          },
          {
            "source_start_frame": 28978,
            "source_end_frame": 29259.999999999,
            "start_frame": 28978,
            "end_frame": 29259,
            "enabled": true
          },
          {
            "source_start_frame": 29260,
            "source_end_frame": 29348.999999999,
            "start_frame": 29260,
            "end_frame": 29348,
            "enabled": false
          },
          {
            "source_start_frame": 29349,
            "source_end_frame": 29430.999999999,
            "start_frame": 29349,
            "end_frame": 29430,
            "enabled": true
          },
          {
            "source_start_frame": 29431,
            "source_end_frame": 29467.999999999,
            "start_frame": 29431,
            "end_frame": 29467,
            "enabled": false
          },
          {
            "source_start_frame": 29468,
            "source_end_frame": 29484,
            "start_frame": 29468,
            "end_frame": 29483,
            "enabled": true
          }
        ],
        "source_channel": 0,
        "type": "Zusammengesetzt",
        "nested_clips": [
          {
            "source_file_path": "/home/oliwoli/Videos/P1466663.MOV",
            "processed_file_name": "f4d8a3a878cb54a482beef75815913da.wav",
            "start_frame": 0,
            "end_frame": 324.99967499999997,
            "source_start_frame": 793.9992060001107,
            "source_end_frame": 1118.9988810001107,
            "duration": 324.99967499999997,
            "source_channel": 1,
            "edit_instructions": []
          },
          {
            "source_file_path": "/home/oliwoli/Videos/P1466663.MOV",
            "processed_file_name": "f4d8a3a878cb54a482beef75815913da.wav",
            "start_frame": 398,
            "end_frame": 29482.970915,
            "source_start_frame": 0,
            "source_end_frame": 29084.970915,
            "duration": 29084.970915,
            "source_channel": 1,
            "edit_instructions": []
          }
        ]
      }
    ]
  },
  "files": {}
}